{
  "/assets/images/portfolio/alejowe-arboretum/slider-11.jpg": {
    "filename": "slider-11.jpg",
    "project": "alejowe-arboretum",
    "strategy": "downloaded-suffix",
    "sourceType": "downloaded",
    "sourceUrl": "../downloaded-portfolio-images/Alejowe-Arboretum-slider-11.jpg",
    "confidence": 95,
    "posts": [
      "alejowe-arboretum.md"
    ]
  },
  "/assets/images/portfolio/alejowe-arboretum/zdj-1.jpg": {
    "filename": "zdj-1.jpg",
    "project": "alejowe-arboretum",
    "strategy": "downloaded-suffix",
    "sourceType": "downloaded",
    "sourceUrl": "../downloaded-portfolio-images/Alejowe-Arboretum-zdj-1.jpg",
    "confidence": 95,
    "posts": [
      "alejowe-arboretum.md"
    ]
  },
  "/assets/images/portfolio/alejowe-arboretum/zdj-2.jpg": {
    "filename": "zdj-2.jpg",
    "project": "alejowe-arboretum",
    "strategy": "downloaded-suffix",
    "sourceType": "downloaded",
    "sourceUrl": "../downloaded-portfolio-images/Alejowe-Arboretum-zdj-2.jpg",
    "confidence": 95,
    "posts": [
      "alejowe-arboretum.md"
    ]
  },
  "/assets/images/portfolio/alejowe-arboretum/zdj-3.jpg": {
    "filename": "zdj-3.jpg",
    "project": "alejowe-arboretum",
    "strategy": "downloaded-suffix",
    "sourceType": "downloaded",
    "sourceUrl": "../downloaded-portfolio-images/Alejowe-Arboretum-zdj-3.jpg",
    "confidence": 95,
    "posts": [
      "alejowe-arboretum.md"
    ]
  },
  "/assets/images/portfolio/alejowe-arboretum/zdj-4.jpg": {
    "filename": "zdj-4.jpg",
    "project": "alejowe-arboretum",
    "strategy": "downloaded-suffix",
    "sourceType": "downloaded",
    "sourceUrl": "../downloaded-portfolio-images/Alejowe-Arboretum-zdj-4.jpg",
    "confidence": 95,
    "posts": [
      "alejowe-arboretum.md"
    ]
  },
  "/assets/images/portfolio/alejowe-arboretum/zdj-5.jpg": {
    "filename": "zdj-5.jpg",
    "project": "alejowe-arboretum",
    "strategy": "downloaded-suffix",
    "sourceType": "downloaded",
    "sourceUrl": "../downloaded-portfolio-images/Alejowe-Arboretum-zdj-5.jpg",
    "confidence": 95,
    "posts": [
      "alejowe-arboretum.md"
    ]
  },
  "/assets/images/portfolio/alejowe-arboretum/zdj-6.jpg": {
    "filename": "zdj-6.jpg",
    "project": "alejowe-arboretum",
    "strategy": "downloaded-suffix",
    "sourceType": "downloaded",
    "sourceUrl": "../downloaded-portfolio-images/Alejowe-Arboretum-zdj-6.jpg",
    "confidence": 95,
    "posts": [
      "alejowe-arboretum.md"
    ]
  },
  "/assets/images/portfolio/alejowe-arboretum/zdj-7.jpg": {
    "filename": "zdj-7.jpg",
    "project": "alejowe-arboretum",
    "strategy": "downloaded-suffix",
    "sourceType": "downloaded",
    "sourceUrl": "../downloaded-portfolio-images/Alejowe-Arboretum-zdj-7.jpg",
    "confidence": 95,
    "posts": [
      "alejowe-arboretum.md"
    ]
  },
  "/assets/images/portfolio/alejowe-arboretum/zdj-8.jpg": {
    "filename": "zdj-8.jpg",
    "project": "alejowe-arboretum",
    "strategy": "downloaded-suffix",
    "sourceType": "downloaded",
    "sourceUrl": "../downloaded-portfolio-images/Alejowe-Arboretum-zdj-8.jpg",
    "confidence": 95,
    "posts": [
      "alejowe-arboretum.md"
    ]
  },
  "/assets/images/portfolio/alejowe-arboretum/zdj-9.jpg": {
    "filename": "zdj-9.jpg",
    "project": "alejowe-arboretum",
    "strategy": "downloaded-suffix",
    "sourceType": "downloaded",
    "sourceUrl": "../downloaded-portfolio-images/Alejowe-Arboretum-zdj-9.jpg",
    "confidence": 95,
    "posts": [
      "alejowe-arboretum.md"
    ]
  },
  "/assets/images/portfolio/alejowe-arboretum/zdj-10.jpg": {
    "filename": "zdj-10.jpg",
    "project": "alejowe-arboretum",
    "strategy": "downloaded-suffix",
    "sourceType": "downloaded",
    "sourceUrl": "../downloaded-portfolio-images/Alejowe-Arboretum-zdj-10.jpg",
    "confidence": 95,
    "posts": [
      "alejowe-arboretum.md"
    ]
  },
  "/assets/images/portfolio/alejowe-arboretum/zdj-11.jpg": {
    "filename": "zdj-11.jpg",
    "project": "alejowe-arboretum",
    "strategy": "downloaded-suffix",
    "sourceType": "downloaded",
    "sourceUrl": "../downloaded-portfolio-images/Alejowe-Arboretum-zdj-11.jpg",
    "confidence": 95,
    "posts": [
      "alejowe-arboretum.md"
    ]
  },
  "/assets/images/portfolio/cmentarz-w-plocku/main.jpg": {
    "filename": "main.jpg",
    "project": "cmentarz-w-plocku",
    "strategy": "unmatched",
    "sourceType": null,
    "sourceUrl": null,
    "confidence": 0,
    "posts": [
      "cmentarz-w-plocku.md"
    ]
  },
  "/assets/images/portfolio/cmentarz-w-plocku/zdj-1.jpg": {
    "filename": "zdj-1.jpg",
    "project": "cmentarz-w-plocku",
    "strategy": "downloaded-suffix",
    "sourceType": "downloaded",
    "sourceUrl": "../downloaded-portfolio-images/Alejowe-Arboretum-zdj-1.jpg",
    "confidence": 95,
    "posts": [
      "cmentarz-w-plocku.md"
    ]
  },
  "/assets/images/portfolio/cmentarz-w-plocku/zdj-2.jpg": {
    "filename": "zdj-2.jpg",
    "project": "cmentarz-w-plocku",
    "strategy": "downloaded-suffix",
    "sourceType": "downloaded",
    "sourceUrl": "../downloaded-portfolio-images/Alejowe-Arboretum-zdj-2.jpg",
    "confidence": 95,
    "posts": [
      "cmentarz-w-plocku.md"
    ]
  },
  "/assets/images/portfolio/cmentarz-w-plocku/zdj-3.jpg": {
    "filename": "zdj-3.jpg",
    "project": "cmentarz-w-plocku",
    "strategy": "downloaded-suffix",
    "sourceType": "downloaded",
    "sourceUrl": "../downloaded-portfolio-images/Alejowe-Arboretum-zdj-3.jpg",
    "confidence": 95,
    "posts": [
      "cmentarz-w-plocku.md"
    ]
  },
  "/assets/images/portfolio/cmentarz-w-plocku/zdj-4.jpg": {
    "filename": "zdj-4.jpg",
    "project": "cmentarz-w-plocku",
    "strategy": "downloaded-suffix",
    "sourceType": "downloaded",
    "sourceUrl": "../downloaded-portfolio-images/Alejowe-Arboretum-zdj-4.jpg",
    "confidence": 95,
    "posts": [
      "cmentarz-w-plocku.md"
    ]
  },
  "/assets/images/portfolio/cmentarz-w-plocku/zdj-5.jpg": {
    "filename": "zdj-5.jpg",
    "project": "cmentarz-w-plocku",
    "strategy": "downloaded-suffix",
    "sourceType": "downloaded",
    "sourceUrl": "../downloaded-portfolio-images/Alejowe-Arboretum-zdj-5.jpg",
    "confidence": 95,
    "posts": [
      "cmentarz-w-plocku.md"
    ]
  },
  "/assets/images/portfolio/cmentarz-w-plocku/zdj-6.jpg": {
    "filename": "zdj-6.jpg",
    "project": "cmentarz-w-plocku",
    "strategy": "downloaded-suffix",
    "sourceType": "downloaded",
    "sourceUrl": "../downloaded-portfolio-images/Alejowe-Arboretum-zdj-6.jpg",
    "confidence": 95,
    "posts": [
      "cmentarz-w-plocku.md"
    ]
  },
  "/assets/images/portfolio/drogi-dla-natury-w-brwinowie/Szkolenie-Brwin-w-slider-111.jpg": {
    "filename": "Szkolenie-Brwin-w-slider-111.jpg",
    "project": "drogi-dla-natury-w-brwinowie",
    "strategy": "unmatched",
    "sourceType": null,
    "sourceUrl": null,
    "confidence": 0,
    "posts": [
      "drogi-dla-natury-w-brwinowie.md"
    ]
  },
  "/assets/images/portfolio/drogi-dla-natury-w-brwinowie/Szkolenie-Brwin-w-zdj-1-1.jpg": {
    "filename": "Szkolenie-Brwin-w-zdj-1-1.jpg",
    "project": "drogi-dla-natury-w-brwinowie",
    "strategy": "unmatched",
    "sourceType": null,
    "sourceUrl": null,
    "confidence": 0,
    "posts": [
      "drogi-dla-natury-w-brwinowie.md"
    ]
  },
  "/assets/images/portfolio/drogi-dla-natury-w-brwinowie/Szkolenie-Brwin-w-zdj-2.jpg": {
    "filename": "Szkolenie-Brwin-w-zdj-2.jpg",
    "project": "drogi-dla-natury-w-brwinowie",
    "strategy": "unmatched",
    "sourceType": null,
    "sourceUrl": null,
    "confidence": 0,
    "posts": [
      "drogi-dla-natury-w-brwinowie.md"
    ]
  },
  "/assets/images/portfolio/drogi-dla-natury-w-brwinowie/Szkolenie-Brwin-w-zdj-3.jpg": {
    "filename": "Szkolenie-Brwin-w-zdj-3.jpg",
    "project": "drogi-dla-natury-w-brwinowie",
    "strategy": "unmatched",
    "sourceType": null,
    "sourceUrl": null,
    "confidence": 0,
    "posts": [
      "drogi-dla-natury-w-brwinowie.md"
    ]
  },
  "/assets/images/portfolio/drogi-dla-natury-w-brwinowie/Szkolenie-Brwin-w-zdj-4.jpg": {
    "filename": "Szkolenie-Brwin-w-zdj-4.jpg",
    "project": "drogi-dla-natury-w-brwinowie",
    "strategy": "unmatched",
    "sourceType": null,
    "sourceUrl": null,
    "confidence": 0,
    "posts": [
      "drogi-dla-natury-w-brwinowie.md"
    ]
  },
  "/assets/images/portfolio/drzewo-na-placu-budowy/Drzewo-na-placu-budowy-jesion-slider.jpg": {
    "filename": "Drzewo-na-placu-budowy-jesion-slider.jpg",
    "project": "drzewo-na-placu-budowy",
    "strategy": "unmatched",
    "sourceType": null,
    "sourceUrl": null,
    "confidence": 0,
    "posts": [
      "drzewo-na-placu-budowy.md"
    ]
  },
  "/assets/images/portfolio/drzewo-na-placu-budowy/Drzewo-na-placu-budowy-jesion-zdj-1-1.jpg": {
    "filename": "Drzewo-na-placu-budowy-jesion-zdj-1-1.jpg",
    "project": "drzewo-na-placu-budowy",
    "strategy": "unmatched",
    "sourceType": null,
    "sourceUrl": null,
    "confidence": 0,
    "posts": [
      "drzewo-na-placu-budowy.md"
    ]
  },
  "/assets/images/portfolio/drzewo-na-placu-budowy/Drzewo-na-placu-budowy-jesion-zdj-3.jpg": {
    "filename": "Drzewo-na-placu-budowy-jesion-zdj-3.jpg",
    "project": "drzewo-na-placu-budowy",
    "strategy": "unmatched",
    "sourceType": null,
    "sourceUrl": null,
    "confidence": 0,
    "posts": [
      "drzewo-na-placu-budowy.md"
    ]
  },
  "/assets/images/portfolio/drzewo-na-placu-budowy/Drzewo-na-placu-budowy-jesion-zdj-2.jpg": {
    "filename": "Drzewo-na-placu-budowy-jesion-zdj-2.jpg",
    "project": "drzewo-na-placu-budowy",
    "strategy": "unmatched",
    "sourceType": null,
    "sourceUrl": null,
    "confidence": 0,
    "posts": [
      "drzewo-na-placu-budowy.md"
    ]
  },
  "/assets/images/portfolio/ekspertyza-dla-debu-wlosta/main.jpg": {
    "filename": "main.jpg",
    "project": "ekspertyza-dla-debu-wlosta",
    "strategy": "unmatched",
    "sourceType": null,
    "sourceUrl": null,
    "confidence": 0,
    "posts": [
      "ekspertyza-dla-debu-wlosta.md"
    ]
  },
  "/assets/images/portfolio/ekspertyza-dla-debu-wlosta/zdj-1.jpg": {
    "filename": "zdj-1.jpg",
    "project": "ekspertyza-dla-debu-wlosta",
    "strategy": "downloaded-suffix",
    "sourceType": "downloaded",
    "sourceUrl": "../downloaded-portfolio-images/Alejowe-Arboretum-zdj-1.jpg",
    "confidence": 95,
    "posts": [
      "ekspertyza-dla-debu-wlosta.md"
    ]
  },
  "/assets/images/portfolio/ekspertyza-dla-debu-wlosta/zdj-2.jpg": {
    "filename": "zdj-2.jpg",
    "project": "ekspertyza-dla-debu-wlosta",
    "strategy": "downloaded-suffix",
    "sourceType": "downloaded",
    "sourceUrl": "../downloaded-portfolio-images/Alejowe-Arboretum-zdj-2.jpg",
    "confidence": 95,
    "posts": [
      "ekspertyza-dla-debu-wlosta.md"
    ]
  },
  "/assets/images/portfolio/ekspertyza-dla-debu-wlosta/zdj-3.jpg": {
    "filename": "zdj-3.jpg",
    "project": "ekspertyza-dla-debu-wlosta",
    "strategy": "downloaded-suffix",
    "sourceType": "downloaded",
    "sourceUrl": "../downloaded-portfolio-images/Alejowe-Arboretum-zdj-3.jpg",
    "confidence": 95,
    "posts": [
      "ekspertyza-dla-debu-wlosta.md"
    ]
  },
  "/assets/images/portfolio/ekspertyza-pomnikowych-lip-przy-palacu/main.jpg": {
    "filename": "main.jpg",
    "project": "ekspertyza-pomnikowych-lip-przy-palacu",
    "strategy": "unmatched",
    "sourceType": null,
    "sourceUrl": null,
    "confidence": 0,
    "posts": [
      "ekspertyza-pomnikowych-lip-przy-palacu.md"
    ]
  },
  "/assets/images/portfolio/inwentaryzacja-dendrologiczna-z-analiza-mozliwosci-zachowania-drzew/Pawia-zdj-1.jpg": {
    "filename": "Pawia-zdj-1.jpg",
    "project": "inwentaryzacja-dendrologiczna-z-analiza-mozliwosci-zachowania-drzew",
    "strategy": "unmatched",
    "sourceType": null,
    "sourceUrl": null,
    "confidence": 0,
    "posts": [
      "inwentaryzacja-dendrologiczna-z-analiza-mozliwosci-zachowania-drzew.md"
    ]
  },
  "/assets/images/portfolio/inwentaryzacja-dendrologiczna-z-analiza-mozliwosci-zachowania-drzew/Pawia-zdj2.jpg": {
    "filename": "Pawia-zdj2.jpg",
    "project": "inwentaryzacja-dendrologiczna-z-analiza-mozliwosci-zachowania-drzew",
    "strategy": "unmatched",
    "sourceType": null,
    "sourceUrl": null,
    "confidence": 0,
    "posts": [
      "inwentaryzacja-dendrologiczna-z-analiza-mozliwosci-zachowania-drzew.md"
    ]
  },
  "/assets/images/portfolio/inwentaryzacja-dendrologiczna-z-analiza-mozliwosci-zachowania-drzew/Pawia-zdj3.jpg": {
    "filename": "Pawia-zdj3.jpg",
    "project": "inwentaryzacja-dendrologiczna-z-analiza-mozliwosci-zachowania-drzew",
    "strategy": "unmatched",
    "sourceType": null,
    "sourceUrl": null,
    "confidence": 0,
    "posts": [
      "inwentaryzacja-dendrologiczna-z-analiza-mozliwosci-zachowania-drzew.md"
    ]
  },
  "/assets/images/portfolio/inwentaryzacja-dendrologiczna-z-analiza-mozliwosci-zachowania-drzew/Pawia-zdj4.jpg": {
    "filename": "Pawia-zdj4.jpg",
    "project": "inwentaryzacja-dendrologiczna-z-analiza-mozliwosci-zachowania-drzew",
    "strategy": "unmatched",
    "sourceType": null,
    "sourceUrl": null,
    "confidence": 0,
    "posts": [
      "inwentaryzacja-dendrologiczna-z-analiza-mozliwosci-zachowania-drzew.md"
    ]
  },
  "/assets/images/portfolio/inwentaryzacja-dendrologiczna-z-analiza-mozliwosci-zachowania-drzew/Pawia-zdj5.jpg": {
    "filename": "Pawia-zdj5.jpg",
    "project": "inwentaryzacja-dendrologiczna-z-analiza-mozliwosci-zachowania-drzew",
    "strategy": "unmatched",
    "sourceType": null,
    "sourceUrl": null,
    "confidence": 0,
    "posts": [
      "inwentaryzacja-dendrologiczna-z-analiza-mozliwosci-zachowania-drzew.md"
    ]
  },
  "/assets/images/portfolio/konferencja-w-otrebusach/main.jpg": {
    "filename": "main.jpg",
    "project": "konferencja-w-otrebusach",
    "strategy": "unmatched",
    "sourceType": null,
    "sourceUrl": null,
    "confidence": 0,
    "posts": [
      "konferencja-w-otrebusach.md"
    ]
  },
  "/assets/images/portfolio/konferencja-w-otrebusach/zdj-1.jpg": {
    "filename": "zdj-1.jpg",
    "project": "konferencja-w-otrebusach",
    "strategy": "downloaded-suffix",
    "sourceType": "downloaded",
    "sourceUrl": "../downloaded-portfolio-images/Alejowe-Arboretum-zdj-1.jpg",
    "confidence": 95,
    "posts": [
      "konferencja-w-otrebusach.md"
    ]
  },
  "/assets/images/portfolio/konferencja-w-otrebusach/zdj-2.jpg": {
    "filename": "zdj-2.jpg",
    "project": "konferencja-w-otrebusach",
    "strategy": "downloaded-suffix",
    "sourceType": "downloaded",
    "sourceUrl": "../downloaded-portfolio-images/Alejowe-Arboretum-zdj-2.jpg",
    "confidence": 95,
    "posts": [
      "konferencja-w-otrebusach.md"
    ]
  },
  "/assets/images/portfolio/konferencja-w-otrebusach/zdj-3.jpg": {
    "filename": "zdj-3.jpg",
    "project": "konferencja-w-otrebusach",
    "strategy": "downloaded-suffix",
    "sourceType": "downloaded",
    "sourceUrl": "../downloaded-portfolio-images/Alejowe-Arboretum-zdj-3.jpg",
    "confidence": 95,
    "posts": [
      "konferencja-w-otrebusach.md"
    ]
  },
  "/assets/images/portfolio/konferencja-w-otrebusach/zdj-4.jpg": {
    "filename": "zdj-4.jpg",
    "project": "konferencja-w-otrebusach",
    "strategy": "downloaded-suffix",
    "sourceType": "downloaded",
    "sourceUrl": "../downloaded-portfolio-images/Alejowe-Arboretum-zdj-4.jpg",
    "confidence": 95,
    "posts": [
      "konferencja-w-otrebusach.md"
    ]
  },
  "/assets/images/portfolio/konferencja-w-otrebusach/zdj-5.jpg": {
    "filename": "zdj-5.jpg",
    "project": "konferencja-w-otrebusach",
    "strategy": "downloaded-suffix",
    "sourceType": "downloaded",
    "sourceUrl": "../downloaded-portfolio-images/Alejowe-Arboretum-zdj-5.jpg",
    "confidence": 95,
    "posts": [
      "konferencja-w-otrebusach.md"
    ]
  },
  "/assets/images/portfolio/kurort-nadmorski-swinoujscie/main.jpg": {
    "filename": "main.jpg",
    "project": "kurort-nadmorski-swinoujscie",
    "strategy": "unmatched",
    "sourceType": null,
    "sourceUrl": null,
    "confidence": 0,
    "posts": [
      "kurort-nadmorski-swinoujscie.md"
    ]
  },
  "/assets/images/portfolio/kwiaty-na-rondzie-ogrod-miejski/IKROPKA_KWIATY-NA-RONDZIE-PODSTAWOWY2-min.jpg": {
    "filename": "IKROPKA_KWIATY-NA-RONDZIE-PODSTAWOWY2-min.jpg",
    "project": "kwiaty-na-rondzie-ogrod-miejski",
    "strategy": "unmatched",
    "sourceType": null,
    "sourceUrl": null,
    "confidence": 0,
    "posts": [
      "kwiaty-na-rondzie-ogrod-miejski.md"
    ]
  },
  "/assets/images/portfolio/kwiaty-na-rondzie-ogrod-miejski/ikropka-rondo-3-min.jpg": {
    "filename": "ikropka-rondo-3-min.jpg",
    "project": "kwiaty-na-rondzie-ogrod-miejski",
    "strategy": "unmatched",
    "sourceType": null,
    "sourceUrl": null,
    "confidence": 0,
    "posts": [
      "kwiaty-na-rondzie-ogrod-miejski.md"
    ]
  },
  "/assets/images/portfolio/kwiaty-na-rondzie-ogrod-miejski/ikropka-rondo-powstańców-śląskich3.jpg": {
    "filename": "ikropka-rondo-powstańców-śląskich3.jpg",
    "project": "kwiaty-na-rondzie-ogrod-miejski",
    "strategy": "unmatched",
    "sourceType": null,
    "sourceUrl": null,
    "confidence": 0,
    "posts": [
      "kwiaty-na-rondzie-ogrod-miejski.md"
    ]
  },
  "/assets/images/portfolio/kwiaty-na-rondzie-ogrod-miejski/ikropka-rondo-powstańców-śląskich1.jpg": {
    "filename": "ikropka-rondo-powstańców-śląskich1.jpg",
    "project": "kwiaty-na-rondzie-ogrod-miejski",
    "strategy": "unmatched",
    "sourceType": null,
    "sourceUrl": null,
    "confidence": 0,
    "posts": [
      "kwiaty-na-rondzie-ogrod-miejski.md"
    ]
  },
  "/assets/images/portfolio/kwiaty-na-rondzie-ogrod-miejski/ikropka-rondo-2-min.jpg": {
    "filename": "ikropka-rondo-2-min.jpg",
    "project": "kwiaty-na-rondzie-ogrod-miejski",
    "strategy": "unmatched",
    "sourceType": null,
    "sourceUrl": null,
    "confidence": 0,
    "posts": [
      "kwiaty-na-rondzie-ogrod-miejski.md"
    ]
  },
  "/assets/images/portfolio/kwiaty-na-rondzie-ogrod-miejski/ikropka-rondo-9-min.jpg": {
    "filename": "ikropka-rondo-9-min.jpg",
    "project": "kwiaty-na-rondzie-ogrod-miejski",
    "strategy": "unmatched",
    "sourceType": null,
    "sourceUrl": null,
    "confidence": 0,
    "posts": [
      "kwiaty-na-rondzie-ogrod-miejski.md"
    ]
  },
  "/assets/images/portfolio/kwiaty-na-rondzie-ogrod-miejski/ikropka-rondo-5-min.jpg": {
    "filename": "ikropka-rondo-5-min.jpg",
    "project": "kwiaty-na-rondzie-ogrod-miejski",
    "strategy": "unmatched",
    "sourceType": null,
    "sourceUrl": null,
    "confidence": 0,
    "posts": [
      "kwiaty-na-rondzie-ogrod-miejski.md"
    ]
  },
  "/assets/images/portfolio/kwiaty-na-rondzie-ogrod-miejski/ikropka-rondo-1-min.jpg": {
    "filename": "ikropka-rondo-1-min.jpg",
    "project": "kwiaty-na-rondzie-ogrod-miejski",
    "strategy": "unmatched",
    "sourceType": null,
    "sourceUrl": null,
    "confidence": 0,
    "posts": [
      "kwiaty-na-rondzie-ogrod-miejski.md"
    ]
  },
  "/assets/images/portfolio/kwiaty-na-rondzie-ogrod-miejski/ikropka-rondo-4-min.jpg": {
    "filename": "ikropka-rondo-4-min.jpg",
    "project": "kwiaty-na-rondzie-ogrod-miejski",
    "strategy": "unmatched",
    "sourceType": null,
    "sourceUrl": null,
    "confidence": 0,
    "posts": [
      "kwiaty-na-rondzie-ogrod-miejski.md"
    ]
  },
  "/assets/images/portfolio/kwiaty-na-rondzie-ogrod-miejski/IKROPKA_KWIATY-NA-RONDZIE-PODSTAWOWY-min.jpg": {
    "filename": "IKROPKA_KWIATY-NA-RONDZIE-PODSTAWOWY-min.jpg",
    "project": "kwiaty-na-rondzie-ogrod-miejski",
    "strategy": "unmatched",
    "sourceType": null,
    "sourceUrl": null,
    "confidence": 0,
    "posts": [
      "kwiaty-na-rondzie-ogrod-miejski.md"
    ]
  },
  "/assets/images/portfolio/kwiaty-na-rondzie-ogrod-miejski/kwiaty-na-rondzie_ikropka_zdj1.jpg": {
    "filename": "kwiaty-na-rondzie_ikropka_zdj1.jpg",
    "project": "kwiaty-na-rondzie-ogrod-miejski",
    "strategy": "unmatched",
    "sourceType": null,
    "sourceUrl": null,
    "confidence": 0,
    "posts": [
      "kwiaty-na-rondzie-ogrod-miejski.md"
    ]
  },
  "/assets/images/portfolio/kwiaty-na-rondzie-ogrod-miejski/kwiaty-na-rondzie_ikropka_zdj10.jpg": {
    "filename": "kwiaty-na-rondzie_ikropka_zdj10.jpg",
    "project": "kwiaty-na-rondzie-ogrod-miejski",
    "strategy": "unmatched",
    "sourceType": null,
    "sourceUrl": null,
    "confidence": 0,
    "posts": [
      "kwiaty-na-rondzie-ogrod-miejski.md"
    ]
  },
  "/assets/images/portfolio/kwiaty-na-rondzie-ogrod-miejski/kwiaty-na-rondzie_ikropka_zdj30.jpg": {
    "filename": "kwiaty-na-rondzie_ikropka_zdj30.jpg",
    "project": "kwiaty-na-rondzie-ogrod-miejski",
    "strategy": "unmatched",
    "sourceType": null,
    "sourceUrl": null,
    "confidence": 0,
    "posts": [
      "kwiaty-na-rondzie-ogrod-miejski.md"
    ]
  },
  "/assets/images/portfolio/kwiaty-na-rondzie-ogrod-miejski/kwiaty-na-rondzie_ikropka_zdj40.jpg": {
    "filename": "kwiaty-na-rondzie_ikropka_zdj40.jpg",
    "project": "kwiaty-na-rondzie-ogrod-miejski",
    "strategy": "unmatched",
    "sourceType": null,
    "sourceUrl": null,
    "confidence": 0,
    "posts": [
      "kwiaty-na-rondzie-ogrod-miejski.md"
    ]
  },
  "/assets/images/portfolio/kwiaty-na-rondzie-ogrod-miejski/kwiaty-na-rondzie_ikropka_zdj50.jpg": {
    "filename": "kwiaty-na-rondzie_ikropka_zdj50.jpg",
    "project": "kwiaty-na-rondzie-ogrod-miejski",
    "strategy": "unmatched",
    "sourceType": null,
    "sourceUrl": null,
    "confidence": 0,
    "posts": [
      "kwiaty-na-rondzie-ogrod-miejski.md"
    ]
  },
  "/assets/images/portfolio/kwiaty-na-rondzie-ogrod-miejski/kwiaty-na-rondzie_ikropka_zdj61.jpg": {
    "filename": "kwiaty-na-rondzie_ikropka_zdj61.jpg",
    "project": "kwiaty-na-rondzie-ogrod-miejski",
    "strategy": "unmatched",
    "sourceType": null,
    "sourceUrl": null,
    "confidence": 0,
    "posts": [
      "kwiaty-na-rondzie-ogrod-miejski.md"
    ]
  },
  "/assets/images/portfolio/kwiaty-na-rondzie-ogrod-miejski/kwiaty-na-rondzie_ikropka_zdj70.jpg": {
    "filename": "kwiaty-na-rondzie_ikropka_zdj70.jpg",
    "project": "kwiaty-na-rondzie-ogrod-miejski",
    "strategy": "unmatched",
    "sourceType": null,
    "sourceUrl": null,
    "confidence": 0,
    "posts": [
      "kwiaty-na-rondzie-ogrod-miejski.md"
    ]
  },
  "/assets/images/portfolio/kwiaty-na-rondzie-ogrod-miejski/kwiaty-na-rondzie_ikropka_zdj80.jpg": {
    "filename": "kwiaty-na-rondzie_ikropka_zdj80.jpg",
    "project": "kwiaty-na-rondzie-ogrod-miejski",
    "strategy": "unmatched",
    "sourceType": null,
    "sourceUrl": null,
    "confidence": 0,
    "posts": [
      "kwiaty-na-rondzie-ogrod-miejski.md"
    ]
  },
  "/assets/images/portfolio/kwiaty-na-rondzie-ogrod-miejski/kwiaty-na-rondzie_ikropka_zdj90.jpg": {
    "filename": "kwiaty-na-rondzie_ikropka_zdj90.jpg",
    "project": "kwiaty-na-rondzie-ogrod-miejski",
    "strategy": "unmatched",
    "sourceType": null,
    "sourceUrl": null,
    "confidence": 0,
    "posts": [
      "kwiaty-na-rondzie-ogrod-miejski.md"
    ]
  },
  "/assets/images/portfolio/kwiaty-na-rondzie-ogrod-miejski/kwiaty-na-rondzie_ikropka_zdj91.jpg": {
    "filename": "kwiaty-na-rondzie_ikropka_zdj91.jpg",
    "project": "kwiaty-na-rondzie-ogrod-miejski",
    "strategy": "unmatched",
    "sourceType": null,
    "sourceUrl": null,
    "confidence": 0,
    "posts": [
      "kwiaty-na-rondzie-ogrod-miejski.md"
    ]
  },
  "/assets/images/portfolio/modelowe-osiedle-nowe-zerniki-wuwa-2/main.jpg": {
    "filename": "main.jpg",
    "project": "modelowe-osiedle-nowe-zerniki-wuwa-2",
    "strategy": "unmatched",
    "sourceType": null,
    "sourceUrl": null,
    "confidence": 0,
    "posts": [
      "modelowe-osiedle-nowe-zerniki-wuwa-2.md"
    ]
  },
  "/assets/images/portfolio/modelowe-osiedle-nowe-zerniki-wuwa-2/photo1.jpg": {
    "filename": "photo1.jpg",
    "project": "modelowe-osiedle-nowe-zerniki-wuwa-2",
    "strategy": "unmatched",
    "sourceType": null,
    "sourceUrl": null,
    "confidence": 0,
    "posts": [
      "modelowe-osiedle-nowe-zerniki-wuwa-2.md"
    ]
  },
  "/assets/images/portfolio/modelowe-osiedle-nowe-zerniki-wuwa-2/photo2.jpg": {
    "filename": "photo2.jpg",
    "project": "modelowe-osiedle-nowe-zerniki-wuwa-2",
    "strategy": "unmatched",
    "sourceType": null,
    "sourceUrl": null,
    "confidence": 0,
    "posts": [
      "modelowe-osiedle-nowe-zerniki-wuwa-2.md"
    ]
  },
  "/assets/images/portfolio/modelowe-osiedle-nowe-zerniki-wuwa-2/photo3.jpg": {
    "filename": "photo3.jpg",
    "project": "modelowe-osiedle-nowe-zerniki-wuwa-2",
    "strategy": "unmatched",
    "sourceType": null,
    "sourceUrl": null,
    "confidence": 0,
    "posts": [
      "modelowe-osiedle-nowe-zerniki-wuwa-2.md"
    ]
  },
  "/assets/images/portfolio/modelowe-osiedle-nowe-zerniki-wuwa-2/photo4.jpg": {
    "filename": "photo4.jpg",
    "project": "modelowe-osiedle-nowe-zerniki-wuwa-2",
    "strategy": "unmatched",
    "sourceType": null,
    "sourceUrl": null,
    "confidence": 0,
    "posts": [
      "modelowe-osiedle-nowe-zerniki-wuwa-2.md"
    ]
  },
  "/assets/images/portfolio/modelowe-osiedle-nowe-zerniki-wuwa-2/photo5.jpg": {
    "filename": "photo5.jpg",
    "project": "modelowe-osiedle-nowe-zerniki-wuwa-2",
    "strategy": "unmatched",
    "sourceType": null,
    "sourceUrl": null,
    "confidence": 0,
    "posts": [
      "modelowe-osiedle-nowe-zerniki-wuwa-2.md"
    ]
  },
  "/assets/images/portfolio/modelowe-osiedle-nowe-zerniki-wuwa-2/photo6.jpg": {
    "filename": "photo6.jpg",
    "project": "modelowe-osiedle-nowe-zerniki-wuwa-2",
    "strategy": "unmatched",
    "sourceType": null,
    "sourceUrl": null,
    "confidence": 0,
    "posts": [
      "modelowe-osiedle-nowe-zerniki-wuwa-2.md"
    ]
  },
  "/assets/images/portfolio/modelowe-osiedle-nowe-zerniki-wuwa-2/photo7.jpg": {
    "filename": "photo7.jpg",
    "project": "modelowe-osiedle-nowe-zerniki-wuwa-2",
    "strategy": "unmatched",
    "sourceType": null,
    "sourceUrl": null,
    "confidence": 0,
    "posts": [
      "modelowe-osiedle-nowe-zerniki-wuwa-2.md"
    ]
  },
  "/assets/images/portfolio/modelowe-osiedle-nowe-zerniki-wuwa-2/photo8.jpg": {
    "filename": "photo8.jpg",
    "project": "modelowe-osiedle-nowe-zerniki-wuwa-2",
    "strategy": "unmatched",
    "sourceType": null,
    "sourceUrl": null,
    "confidence": 0,
    "posts": [
      "modelowe-osiedle-nowe-zerniki-wuwa-2.md"
    ]
  },
  "/assets/images/portfolio/na-prudnickim-cmentarzu/slider111.jpg": {
    "filename": "slider111.jpg",
    "project": "na-prudnickim-cmentarzu",
    "strategy": "downloaded-suffix",
    "sourceType": "downloaded",
    "sourceUrl": "../downloaded-portfolio-images/Nadz-r-Platan-slider111.jpg",
    "confidence": 95,
    "posts": [
      "na-prudnickim-cmentarzu.md"
    ]
  },
  "/assets/images/portfolio/na-prudnickim-cmentarzu/zdj-1-1.jpg": {
    "filename": "zdj-1-1.jpg",
    "project": "na-prudnickim-cmentarzu",
    "strategy": "downloaded-suffix",
    "sourceType": "downloaded",
    "sourceUrl": "../downloaded-portfolio-images/Bialaczow-zdj-1-1.jpg",
    "confidence": 95,
    "posts": [
      "na-prudnickim-cmentarzu.md"
    ]
  },
  "/assets/images/portfolio/na-prudnickim-cmentarzu/zdj-3.jpg": {
    "filename": "zdj-3.jpg",
    "project": "na-prudnickim-cmentarzu",
    "strategy": "downloaded-suffix",
    "sourceType": "downloaded",
    "sourceUrl": "../downloaded-portfolio-images/Alejowe-Arboretum-zdj-3.jpg",
    "confidence": 95,
    "posts": [
      "na-prudnickim-cmentarzu.md"
    ]
  },
  "/assets/images/portfolio/na-prudnickim-cmentarzu/zdj-4.jpg": {
    "filename": "zdj-4.jpg",
    "project": "na-prudnickim-cmentarzu",
    "strategy": "downloaded-suffix",
    "sourceType": "downloaded",
    "sourceUrl": "../downloaded-portfolio-images/Alejowe-Arboretum-zdj-4.jpg",
    "confidence": 95,
    "posts": [
      "na-prudnickim-cmentarzu.md"
    ]
  },
  "/assets/images/portfolio/na-prudnickim-cmentarzu/zdj-5.jpg": {
    "filename": "zdj-5.jpg",
    "project": "na-prudnickim-cmentarzu",
    "strategy": "downloaded-suffix",
    "sourceType": "downloaded",
    "sourceUrl": "../downloaded-portfolio-images/Alejowe-Arboretum-zdj-5.jpg",
    "confidence": 95,
    "posts": [
      "na-prudnickim-cmentarzu.md"
    ]
  },
  "/assets/images/portfolio/na-prudnickim-cmentarzu/zdj-6.jpg": {
    "filename": "zdj-6.jpg",
    "project": "na-prudnickim-cmentarzu",
    "strategy": "downloaded-suffix",
    "sourceType": "downloaded",
    "sourceUrl": "../downloaded-portfolio-images/Alejowe-Arboretum-zdj-6.jpg",
    "confidence": 95,
    "posts": [
      "na-prudnickim-cmentarzu.md"
    ]
  },
  "/assets/images/portfolio/nadzor-dendrologiczny-platan-przy-nowej-izbie-skarbowej/slider111.jpg": {
    "filename": "slider111.jpg",
    "project": "nadzor-dendrologiczny-platan-przy-nowej-izbie-skarbowej",
    "strategy": "downloaded-suffix",
    "sourceType": "downloaded",
    "sourceUrl": "../downloaded-portfolio-images/Nadz-r-Platan-slider111.jpg",
    "confidence": 95,
    "posts": [
      "nadzor-dendrologiczny-platan-przy-nowej-izbie-skarbowej.md"
    ]
  },
  "/assets/images/portfolio/nadzor-dendrologiczny-platan-przy-nowej-izbie-skarbowej/zdj-1-1.jpg": {
    "filename": "zdj-1-1.jpg",
    "project": "nadzor-dendrologiczny-platan-przy-nowej-izbie-skarbowej",
    "strategy": "downloaded-suffix",
    "sourceType": "downloaded",
    "sourceUrl": "../downloaded-portfolio-images/Bialaczow-zdj-1-1.jpg",
    "confidence": 95,
    "posts": [
      "nadzor-dendrologiczny-platan-przy-nowej-izbie-skarbowej.md"
    ]
  },
  "/assets/images/portfolio/nadzor-dendrologiczny-platan-przy-nowej-izbie-skarbowej/zdj-2.jpg": {
    "filename": "zdj-2.jpg",
    "project": "nadzor-dendrologiczny-platan-przy-nowej-izbie-skarbowej",
    "strategy": "downloaded-suffix",
    "sourceType": "downloaded",
    "sourceUrl": "../downloaded-portfolio-images/Alejowe-Arboretum-zdj-2.jpg",
    "confidence": 95,
    "posts": [
      "nadzor-dendrologiczny-platan-przy-nowej-izbie-skarbowej.md"
    ]
  },
  "/assets/images/portfolio/nadzor-dendrologiczny-platan-przy-nowej-izbie-skarbowej/zdj-3.jpg": {
    "filename": "zdj-3.jpg",
    "project": "nadzor-dendrologiczny-platan-przy-nowej-izbie-skarbowej",
    "strategy": "downloaded-suffix",
    "sourceType": "downloaded",
    "sourceUrl": "../downloaded-portfolio-images/Alejowe-Arboretum-zdj-3.jpg",
    "confidence": 95,
    "posts": [
      "nadzor-dendrologiczny-platan-przy-nowej-izbie-skarbowej.md"
    ]
  },
  "/assets/images/portfolio/nadzor-dendrologiczny-platan-przy-nowej-izbie-skarbowej/zdj-4.jpg": {
    "filename": "zdj-4.jpg",
    "project": "nadzor-dendrologiczny-platan-przy-nowej-izbie-skarbowej",
    "strategy": "downloaded-suffix",
    "sourceType": "downloaded",
    "sourceUrl": "../downloaded-portfolio-images/Alejowe-Arboretum-zdj-4.jpg",
    "confidence": 95,
    "posts": [
      "nadzor-dendrologiczny-platan-przy-nowej-izbie-skarbowej.md"
    ]
  },
  "/assets/images/portfolio/nadzor-dendrologiczny-platan-przy-nowej-izbie-skarbowej/zdj-5.jpg": {
    "filename": "zdj-5.jpg",
    "project": "nadzor-dendrologiczny-platan-przy-nowej-izbie-skarbowej",
    "strategy": "downloaded-suffix",
    "sourceType": "downloaded",
    "sourceUrl": "../downloaded-portfolio-images/Alejowe-Arboretum-zdj-5.jpg",
    "confidence": 95,
    "posts": [
      "nadzor-dendrologiczny-platan-przy-nowej-izbie-skarbowej.md"
    ]
  },
  "/assets/images/portfolio/nadzor-dendrologiczny-platan-przy-nowej-izbie-skarbowej/zdj-6.jpg": {
    "filename": "zdj-6.jpg",
    "project": "nadzor-dendrologiczny-platan-przy-nowej-izbie-skarbowej",
    "strategy": "downloaded-suffix",
    "sourceType": "downloaded",
    "sourceUrl": "../downloaded-portfolio-images/Alejowe-Arboretum-zdj-6.jpg",
    "confidence": 95,
    "posts": [
      "nadzor-dendrologiczny-platan-przy-nowej-izbie-skarbowej.md"
    ]
  },
  "/assets/images/portfolio/nadzor-dendrologiczny-platan-przy-nowej-izbie-skarbowej/zdj-7.jpg": {
    "filename": "zdj-7.jpg",
    "project": "nadzor-dendrologiczny-platan-przy-nowej-izbie-skarbowej",
    "strategy": "downloaded-suffix",
    "sourceType": "downloaded",
    "sourceUrl": "../downloaded-portfolio-images/Alejowe-Arboretum-zdj-7.jpg",
    "confidence": 95,
    "posts": [
      "nadzor-dendrologiczny-platan-przy-nowej-izbie-skarbowej.md"
    ]
  },
  "/assets/images/portfolio/nadzor-dendrologiczny-platan-przy-nowej-izbie-skarbowej/zdj-8.jpg": {
    "filename": "zdj-8.jpg",
    "project": "nadzor-dendrologiczny-platan-przy-nowej-izbie-skarbowej",
    "strategy": "downloaded-suffix",
    "sourceType": "downloaded",
    "sourceUrl": "../downloaded-portfolio-images/Alejowe-Arboretum-zdj-8.jpg",
    "confidence": 95,
    "posts": [
      "nadzor-dendrologiczny-platan-przy-nowej-izbie-skarbowej.md"
    ]
  },
  "/assets/images/portfolio/nadzor-nad-wykonaniem-instalacji-oswietlenia-parku-klecinskim-wroclaw/nadzor-park-klecinski-slider.jpg": {
    "filename": "nadzor-park-klecinski-slider.jpg",
    "project": "nadzor-nad-wykonaniem-instalacji-oswietlenia-parku-klecinskim-wroclaw",
    "strategy": "unmatched",
    "sourceType": null,
    "sourceUrl": null,
    "confidence": 0,
    "posts": [
      "nadzor-nad-wykonaniem-instalacji-oswietlenia-parku-klecinskim-wroclaw.md"
    ]
  },
  "/assets/images/portfolio/nadzor-nad-wykonaniem-instalacji-oswietlenia-parku-klecinskim-wroclaw/nadzor-park-klecinski-zdj.jpg": {
    "filename": "nadzor-park-klecinski-zdj.jpg",
    "project": "nadzor-nad-wykonaniem-instalacji-oswietlenia-parku-klecinskim-wroclaw",
    "strategy": "unmatched",
    "sourceType": null,
    "sourceUrl": null,
    "confidence": 0,
    "posts": [
      "nadzor-nad-wykonaniem-instalacji-oswietlenia-parku-klecinskim-wroclaw.md"
    ]
  },
  "/assets/images/portfolio/nadzor-nad-wykonaniem-instalacji-oswietlenia-parku-klecinskim-wroclaw/nadzor-park-klecinski-zdj3.jpg": {
    "filename": "nadzor-park-klecinski-zdj3.jpg",
    "project": "nadzor-nad-wykonaniem-instalacji-oswietlenia-parku-klecinskim-wroclaw",
    "strategy": "unmatched",
    "sourceType": null,
    "sourceUrl": null,
    "confidence": 0,
    "posts": [
      "nadzor-nad-wykonaniem-instalacji-oswietlenia-parku-klecinskim-wroclaw.md"
    ]
  },
  "/assets/images/portfolio/nadzor-nad-wykonaniem-instalacji-oswietlenia-parku-klecinskim-wroclaw/nadzor-park-klecinski-zdj2.jpg": {
    "filename": "nadzor-park-klecinski-zdj2.jpg",
    "project": "nadzor-nad-wykonaniem-instalacji-oswietlenia-parku-klecinskim-wroclaw",
    "strategy": "unmatched",
    "sourceType": null,
    "sourceUrl": null,
    "confidence": 0,
    "posts": [
      "nadzor-nad-wykonaniem-instalacji-oswietlenia-parku-klecinskim-wroclaw.md"
    ]
  },
  "/assets/images/portfolio/nadzor-nad-wykonaniem-instalacji-oswietlenia-parku-klecinskim-wroclaw/nadzor-park-klecinski-zdj4.jpg": {
    "filename": "nadzor-park-klecinski-zdj4.jpg",
    "project": "nadzor-nad-wykonaniem-instalacji-oswietlenia-parku-klecinskim-wroclaw",
    "strategy": "unmatched",
    "sourceType": null,
    "sourceUrl": null,
    "confidence": 0,
    "posts": [
      "nadzor-nad-wykonaniem-instalacji-oswietlenia-parku-klecinskim-wroclaw.md"
    ]
  },
  "/assets/images/portfolio/nadzor-nad-wykonaniem-instalacji-oswietlenia-parku-klecinskim-wroclaw/nadzor-park-klecinski-zdj6.jpg": {
    "filename": "nadzor-park-klecinski-zdj6.jpg",
    "project": "nadzor-nad-wykonaniem-instalacji-oswietlenia-parku-klecinskim-wroclaw",
    "strategy": "unmatched",
    "sourceType": null,
    "sourceUrl": null,
    "confidence": 0,
    "posts": [
      "nadzor-nad-wykonaniem-instalacji-oswietlenia-parku-klecinskim-wroclaw.md"
    ]
  },
  "/assets/images/portfolio/nadzor-nad-wykonaniem-instalacji-oswietlenia-parku-klecinskim-wroclaw/nadzor-park-klecinski-zdj5.jpg": {
    "filename": "nadzor-park-klecinski-zdj5.jpg",
    "project": "nadzor-nad-wykonaniem-instalacji-oswietlenia-parku-klecinskim-wroclaw",
    "strategy": "unmatched",
    "sourceType": null,
    "sourceUrl": null,
    "confidence": 0,
    "posts": [
      "nadzor-nad-wykonaniem-instalacji-oswietlenia-parku-klecinskim-wroclaw.md"
    ]
  },
  "/assets/images/portfolio/nadzor-przyrodniczy-parku-szczytnickim/main.jpg": {
    "filename": "main.jpg",
    "project": "nadzor-przyrodniczy-parku-szczytnickim",
    "strategy": "unmatched",
    "sourceType": null,
    "sourceUrl": null,
    "confidence": 0,
    "posts": [
      "nadzor-przyrodniczy-parku-szczytnickim.md"
    ]
  },
  "/assets/images/portfolio/nadzor-przyrodniczy-parku-szczytnickim/photo1.jpg": {
    "filename": "photo1.jpg",
    "project": "nadzor-przyrodniczy-parku-szczytnickim",
    "strategy": "unmatched",
    "sourceType": null,
    "sourceUrl": null,
    "confidence": 0,
    "posts": [
      "nadzor-przyrodniczy-parku-szczytnickim.md"
    ]
  },
  "/assets/images/portfolio/nadzor-przyrodniczy-parku-szczytnickim/photo2.jpg": {
    "filename": "photo2.jpg",
    "project": "nadzor-przyrodniczy-parku-szczytnickim",
    "strategy": "unmatched",
    "sourceType": null,
    "sourceUrl": null,
    "confidence": 0,
    "posts": [
      "nadzor-przyrodniczy-parku-szczytnickim.md"
    ]
  },
  "/assets/images/portfolio/nadzor-przyrodniczy-parku-szczytnickim/photo3.jpg": {
    "filename": "photo3.jpg",
    "project": "nadzor-przyrodniczy-parku-szczytnickim",
    "strategy": "unmatched",
    "sourceType": null,
    "sourceUrl": null,
    "confidence": 0,
    "posts": [
      "nadzor-przyrodniczy-parku-szczytnickim.md"
    ]
  },
  "/assets/images/portfolio/nadzor-przyrodniczy-parku-szczytnickim/photo4.jpg": {
    "filename": "photo4.jpg",
    "project": "nadzor-przyrodniczy-parku-szczytnickim",
    "strategy": "unmatched",
    "sourceType": null,
    "sourceUrl": null,
    "confidence": 0,
    "posts": [
      "nadzor-przyrodniczy-parku-szczytnickim.md"
    ]
  },
  "/assets/images/portfolio/nadzor-przyrodniczy-parku-szczytnickim/photo5.jpg": {
    "filename": "photo5.jpg",
    "project": "nadzor-przyrodniczy-parku-szczytnickim",
    "strategy": "unmatched",
    "sourceType": null,
    "sourceUrl": null,
    "confidence": 0,
    "posts": [
      "nadzor-przyrodniczy-parku-szczytnickim.md"
    ]
  },
  "/assets/images/portfolio/nadzor-przyrodniczy-parku-szczytnickim/photo6.jpg": {
    "filename": "photo6.jpg",
    "project": "nadzor-przyrodniczy-parku-szczytnickim",
    "strategy": "unmatched",
    "sourceType": null,
    "sourceUrl": null,
    "confidence": 0,
    "posts": [
      "nadzor-przyrodniczy-parku-szczytnickim.md"
    ]
  },
  "/assets/images/portfolio/nadzor-przyrodniczy-parku-szczytnickim/photo7.jpg": {
    "filename": "photo7.jpg",
    "project": "nadzor-przyrodniczy-parku-szczytnickim",
    "strategy": "unmatched",
    "sourceType": null,
    "sourceUrl": null,
    "confidence": 0,
    "posts": [
      "nadzor-przyrodniczy-parku-szczytnickim.md"
    ]
  },
  "/assets/images/portfolio/nadzor-przyrodniczy-parku-szczytnickim/photo8.jpg": {
    "filename": "photo8.jpg",
    "project": "nadzor-przyrodniczy-parku-szczytnickim",
    "strategy": "unmatched",
    "sourceType": null,
    "sourceUrl": null,
    "confidence": 0,
    "posts": [
      "nadzor-przyrodniczy-parku-szczytnickim.md"
    ]
  },
  "/assets/images/portfolio/nadzor-przyrodniczy-parku-szczytnickim/photo9.jpg": {
    "filename": "photo9.jpg",
    "project": "nadzor-przyrodniczy-parku-szczytnickim",
    "strategy": "unmatched",
    "sourceType": null,
    "sourceUrl": null,
    "confidence": 0,
    "posts": [
      "nadzor-przyrodniczy-parku-szczytnickim.md"
    ]
  },
  "/assets/images/portfolio/nadzor-przyrodniczy-parku-szczytnickim/photo10.jpg": {
    "filename": "photo10.jpg",
    "project": "nadzor-przyrodniczy-parku-szczytnickim",
    "strategy": "unmatched",
    "sourceType": null,
    "sourceUrl": null,
    "confidence": 0,
    "posts": [
      "nadzor-przyrodniczy-parku-szczytnickim.md"
    ]
  },
  "/assets/images/portfolio/nadzor-przyrodniczy-parku-szczytnickim/photo11.jpg": {
    "filename": "photo11.jpg",
    "project": "nadzor-przyrodniczy-parku-szczytnickim",
    "strategy": "unmatched",
    "sourceType": null,
    "sourceUrl": null,
    "confidence": 0,
    "posts": [
      "nadzor-przyrodniczy-parku-szczytnickim.md"
    ]
  },
  "/assets/images/portfolio/nadzor-przyrodniczy-parku-szczytnickim/photo12.jpg": {
    "filename": "photo12.jpg",
    "project": "nadzor-przyrodniczy-parku-szczytnickim",
    "strategy": "unmatched",
    "sourceType": null,
    "sourceUrl": null,
    "confidence": 0,
    "posts": [
      "nadzor-przyrodniczy-parku-szczytnickim.md"
    ]
  },
  "/assets/images/portfolio/naturalistyczny-ogrod-ze-stawem/main.jpg": {
    "filename": "main.jpg",
    "project": "naturalistyczny-ogrod-ze-stawem",
    "strategy": "unmatched",
    "sourceType": null,
    "sourceUrl": null,
    "confidence": 0,
    "posts": [
      "naturalistyczny-ogrod-ze-stawem.md"
    ]
  },
  "/assets/images/portfolio/naturalistyczny-ogrod-ze-stawem/photo1.jpg": {
    "filename": "photo1.jpg",
    "project": "naturalistyczny-ogrod-ze-stawem",
    "strategy": "unmatched",
    "sourceType": null,
    "sourceUrl": null,
    "confidence": 0,
    "posts": [
      "naturalistyczny-ogrod-ze-stawem.md"
    ]
  },
  "/assets/images/portfolio/naturalistyczny-ogrod-ze-stawem/photo2.jpg": {
    "filename": "photo2.jpg",
    "project": "naturalistyczny-ogrod-ze-stawem",
    "strategy": "unmatched",
    "sourceType": null,
    "sourceUrl": null,
    "confidence": 0,
    "posts": [
      "naturalistyczny-ogrod-ze-stawem.md"
    ]
  },
  "/assets/images/portfolio/naturalistyczny-ogrod-ze-stawem/photo3.jpg": {
    "filename": "photo3.jpg",
    "project": "naturalistyczny-ogrod-ze-stawem",
    "strategy": "unmatched",
    "sourceType": null,
    "sourceUrl": null,
    "confidence": 0,
    "posts": [
      "naturalistyczny-ogrod-ze-stawem.md"
    ]
  },
  "/assets/images/portfolio/naturalistyczny-ogrod-ze-stawem/photo4.jpg": {
    "filename": "photo4.jpg",
    "project": "naturalistyczny-ogrod-ze-stawem",
    "strategy": "unmatched",
    "sourceType": null,
    "sourceUrl": null,
    "confidence": 0,
    "posts": [
      "naturalistyczny-ogrod-ze-stawem.md"
    ]
  },
  "/assets/images/portfolio/naturalistyczny-ogrod-ze-stawem/photo5.jpg": {
    "filename": "photo5.jpg",
    "project": "naturalistyczny-ogrod-ze-stawem",
    "strategy": "unmatched",
    "sourceType": null,
    "sourceUrl": null,
    "confidence": 0,
    "posts": [
      "naturalistyczny-ogrod-ze-stawem.md"
    ]
  },
  "/assets/images/portfolio/ocena-zniszczen-drzewa/main.jpg": {
    "filename": "main.jpg",
    "project": "ocena-zniszczen-drzewa",
    "strategy": "unmatched",
    "sourceType": null,
    "sourceUrl": null,
    "confidence": 0,
    "posts": [
      "ocena-zniszczen-drzewa.md"
    ]
  },
  "/assets/images/portfolio/ochrona-zarzadzanie-drzewostanem/main.jpg": {
    "filename": "main.jpg",
    "project": "ochrona-zarzadzanie-drzewostanem",
    "strategy": "unmatched",
    "sourceType": null,
    "sourceUrl": null,
    "confidence": 0,
    "posts": [
      "ochrona-zarzadzanie-drzewostanem.md"
    ]
  },
  "/assets/images/portfolio/ogrod-na-zlotnikach/slider2.jpg": {
    "filename": "slider2.jpg",
    "project": "ogrod-na-zlotnikach",
    "strategy": "downloaded-suffix",
    "sourceType": "downloaded",
    "sourceUrl": "../downloaded-portfolio-images/Ogrod-na-Zlotnikach-slider2.jpg",
    "confidence": 95,
    "posts": [
      "ogrod-na-zlotnikach.md"
    ]
  },
  "/assets/images/portfolio/ogrod-na-zlotnikach/zdj-1.jpg": {
    "filename": "zdj-1.jpg",
    "project": "ogrod-na-zlotnikach",
    "strategy": "downloaded-suffix",
    "sourceType": "downloaded",
    "sourceUrl": "../downloaded-portfolio-images/Alejowe-Arboretum-zdj-1.jpg",
    "confidence": 95,
    "posts": [
      "ogrod-na-zlotnikach.md"
    ]
  },
  "/assets/images/portfolio/ogrod-na-zlotnikach/zdj-2.jpg": {
    "filename": "zdj-2.jpg",
    "project": "ogrod-na-zlotnikach",
    "strategy": "downloaded-suffix",
    "sourceType": "downloaded",
    "sourceUrl": "../downloaded-portfolio-images/Alejowe-Arboretum-zdj-2.jpg",
    "confidence": 95,
    "posts": [
      "ogrod-na-zlotnikach.md"
    ]
  },
  "/assets/images/portfolio/ogrod-na-zlotnikach/zdj-3.jpg": {
    "filename": "zdj-3.jpg",
    "project": "ogrod-na-zlotnikach",
    "strategy": "downloaded-suffix",
    "sourceType": "downloaded",
    "sourceUrl": "../downloaded-portfolio-images/Alejowe-Arboretum-zdj-3.jpg",
    "confidence": 95,
    "posts": [
      "ogrod-na-zlotnikach.md"
    ]
  },
  "/assets/images/portfolio/ogrod-na-zlotnikach/zdj-4.jpg": {
    "filename": "zdj-4.jpg",
    "project": "ogrod-na-zlotnikach",
    "strategy": "downloaded-suffix",
    "sourceType": "downloaded",
    "sourceUrl": "../downloaded-portfolio-images/Alejowe-Arboretum-zdj-4.jpg",
    "confidence": 95,
    "posts": [
      "ogrod-na-zlotnikach.md"
    ]
  },
  "/assets/images/portfolio/ogrodek-chusteczkowy/slider11.jpg": {
    "filename": "slider11.jpg",
    "project": "ogrodek-chusteczkowy",
    "strategy": "downloaded-suffix",
    "sourceType": "downloaded",
    "sourceUrl": "../downloaded-portfolio-images/Ekspertyza-4-drzew-slider11.jpg",
    "confidence": 95,
    "posts": [
      "ogrodek-chusteczkowy.md"
    ]
  },
  "/assets/images/portfolio/ogrodek-chusteczkowy/zdj-1-1.jpg": {
    "filename": "zdj-1-1.jpg",
    "project": "ogrodek-chusteczkowy",
    "strategy": "downloaded-suffix",
    "sourceType": "downloaded",
    "sourceUrl": "../downloaded-portfolio-images/Bialaczow-zdj-1-1.jpg",
    "confidence": 95,
    "posts": [
      "ogrodek-chusteczkowy.md"
    ]
  },
  "/assets/images/portfolio/ogrodek-chusteczkowy/zdj-2.jpg": {
    "filename": "zdj-2.jpg",
    "project": "ogrodek-chusteczkowy",
    "strategy": "downloaded-suffix",
    "sourceType": "downloaded",
    "sourceUrl": "../downloaded-portfolio-images/Alejowe-Arboretum-zdj-2.jpg",
    "confidence": 95,
    "posts": [
      "ogrodek-chusteczkowy.md"
    ]
  },
  "/assets/images/portfolio/ogrodek-chusteczkowy/zdj-3.jpg": {
    "filename": "zdj-3.jpg",
    "project": "ogrodek-chusteczkowy",
    "strategy": "downloaded-suffix",
    "sourceType": "downloaded",
    "sourceUrl": "../downloaded-portfolio-images/Alejowe-Arboretum-zdj-3.jpg",
    "confidence": 95,
    "posts": [
      "ogrodek-chusteczkowy.md"
    ]
  },
  "/assets/images/portfolio/ogrodek-chusteczkowy/zdj-4.jpg": {
    "filename": "zdj-4.jpg",
    "project": "ogrodek-chusteczkowy",
    "strategy": "downloaded-suffix",
    "sourceType": "downloaded",
    "sourceUrl": "../downloaded-portfolio-images/Alejowe-Arboretum-zdj-4.jpg",
    "confidence": 95,
    "posts": [
      "ogrodek-chusteczkowy.md"
    ]
  },
  "/assets/images/portfolio/ogrodek-chusteczkowy/zdj-5.jpg": {
    "filename": "zdj-5.jpg",
    "project": "ogrodek-chusteczkowy",
    "strategy": "downloaded-suffix",
    "sourceType": "downloaded",
    "sourceUrl": "../downloaded-portfolio-images/Alejowe-Arboretum-zdj-5.jpg",
    "confidence": 95,
    "posts": [
      "ogrodek-chusteczkowy.md"
    ]
  },
  "/assets/images/portfolio/ogrodek-chusteczkowy/zdj-6.jpg": {
    "filename": "zdj-6.jpg",
    "project": "ogrodek-chusteczkowy",
    "strategy": "downloaded-suffix",
    "sourceType": "downloaded",
    "sourceUrl": "../downloaded-portfolio-images/Alejowe-Arboretum-zdj-6.jpg",
    "confidence": 95,
    "posts": [
      "ogrodek-chusteczkowy.md"
    ]
  },
  "/assets/images/portfolio/ogrodek-chusteczkowy/zdj-7.jpg": {
    "filename": "zdj-7.jpg",
    "project": "ogrodek-chusteczkowy",
    "strategy": "downloaded-suffix",
    "sourceType": "downloaded",
    "sourceUrl": "../downloaded-portfolio-images/Alejowe-Arboretum-zdj-7.jpg",
    "confidence": 95,
    "posts": [
      "ogrodek-chusteczkowy.md"
    ]
  },
  "/assets/images/portfolio/ogrodek-chusteczkowy/zdj-8.jpg": {
    "filename": "zdj-8.jpg",
    "project": "ogrodek-chusteczkowy",
    "strategy": "downloaded-suffix",
    "sourceType": "downloaded",
    "sourceUrl": "../downloaded-portfolio-images/Alejowe-Arboretum-zdj-8.jpg",
    "confidence": 95,
    "posts": [
      "ogrodek-chusteczkowy.md"
    ]
  },
  "/assets/images/portfolio/ogrodek-chusteczkowy/zdj-9.jpg": {
    "filename": "zdj-9.jpg",
    "project": "ogrodek-chusteczkowy",
    "strategy": "downloaded-suffix",
    "sourceType": "downloaded",
    "sourceUrl": "../downloaded-portfolio-images/Alejowe-Arboretum-zdj-9.jpg",
    "confidence": 95,
    "posts": [
      "ogrodek-chusteczkowy.md"
    ]
  },
  "/assets/images/portfolio/operat-dendrologiczny-lagowie/operat-lagow-zdj-1-1.jpg": {
    "filename": "operat-lagow-zdj-1-1.jpg",
    "project": "operat-dendrologiczny-lagowie",
    "strategy": "downloaded-suffix",
    "sourceType": "downloaded",
    "sourceUrl": "../downloaded-portfolio-images/operat-Lagow-zdj-1-1.jpg",
    "confidence": 95,
    "posts": [
      "operat-dendrologiczny-lagowie.md"
    ]
  },
  "/assets/images/portfolio/operat-dendrologiczny-lagowie/operat-lagow-zdj3.jpg": {
    "filename": "operat-lagow-zdj3.jpg",
    "project": "operat-dendrologiczny-lagowie",
    "strategy": "downloaded-suffix",
    "sourceType": "downloaded",
    "sourceUrl": "../downloaded-portfolio-images/operat-Lagow-zdj3.jpg",
    "confidence": 95,
    "posts": [
      "operat-dendrologiczny-lagowie.md"
    ]
  },
  "/assets/images/portfolio/operat-dendrologiczny-lagowie/operat-lagow-zdj4.jpg": {
    "filename": "operat-lagow-zdj4.jpg",
    "project": "operat-dendrologiczny-lagowie",
    "strategy": "downloaded-suffix",
    "sourceType": "downloaded",
    "sourceUrl": "../downloaded-portfolio-images/operat-Lagow-zdj4.jpg",
    "confidence": 95,
    "posts": [
      "operat-dendrologiczny-lagowie.md"
    ]
  },
  "/assets/images/portfolio/operat-dendrologiczny-lagowie/operat-lagow-zdj9.jpg": {
    "filename": "operat-lagow-zdj9.jpg",
    "project": "operat-dendrologiczny-lagowie",
    "strategy": "downloaded-suffix",
    "sourceType": "downloaded",
    "sourceUrl": "../downloaded-portfolio-images/operat-Lagow-zdj9.jpg",
    "confidence": 95,
    "posts": [
      "operat-dendrologiczny-lagowie.md"
    ]
  },
  "/assets/images/portfolio/operat-dendrologiczny-lagowie/operat-lagow-zdj10.jpg": {
    "filename": "operat-lagow-zdj10.jpg",
    "project": "operat-dendrologiczny-lagowie",
    "strategy": "downloaded-suffix",
    "sourceType": "downloaded",
    "sourceUrl": "../downloaded-portfolio-images/operat-Lagow-zdj10.jpg",
    "confidence": 95,
    "posts": [
      "operat-dendrologiczny-lagowie.md"
    ]
  },
  "/assets/images/portfolio/operat-dendrologiczny-lagowie/operat-lagow-zdj11.jpg": {
    "filename": "operat-lagow-zdj11.jpg",
    "project": "operat-dendrologiczny-lagowie",
    "strategy": "downloaded-suffix",
    "sourceType": "downloaded",
    "sourceUrl": "../downloaded-portfolio-images/operat-Lagow-zdj11.jpg",
    "confidence": 95,
    "posts": [
      "operat-dendrologiczny-lagowie.md"
    ]
  },
  "/assets/images/portfolio/operat-dendrologiczny-lagowie/operat-lagow-zdj12.jpg": {
    "filename": "operat-lagow-zdj12.jpg",
    "project": "operat-dendrologiczny-lagowie",
    "strategy": "downloaded-suffix",
    "sourceType": "downloaded",
    "sourceUrl": "../downloaded-portfolio-images/operat-Lagow-zdj12.jpg",
    "confidence": 95,
    "posts": [
      "operat-dendrologiczny-lagowie.md"
    ]
  },
  "/assets/images/portfolio/operat-dendrologiczny-lagowie/operat-lagow-zdj13.jpg": {
    "filename": "operat-lagow-zdj13.jpg",
    "project": "operat-dendrologiczny-lagowie",
    "strategy": "downloaded-suffix",
    "sourceType": "downloaded",
    "sourceUrl": "../downloaded-portfolio-images/operat-Lagow-zdj13.jpg",
    "confidence": 95,
    "posts": [
      "operat-dendrologiczny-lagowie.md"
    ]
  },
  "/assets/images/portfolio/operat-dendrologiczny-lagowie/operat-lagow-zdj17.jpg": {
    "filename": "operat-lagow-zdj17.jpg",
    "project": "operat-dendrologiczny-lagowie",
    "strategy": "downloaded-suffix",
    "sourceType": "downloaded",
    "sourceUrl": "../downloaded-portfolio-images/operat-Lagow-zdj17.jpg",
    "confidence": 95,
    "posts": [
      "operat-dendrologiczny-lagowie.md"
    ]
  },
  "/assets/images/portfolio/operat-dendrologiczny-lagowie/operat-lagow-zdj15.jpg": {
    "filename": "operat-lagow-zdj15.jpg",
    "project": "operat-dendrologiczny-lagowie",
    "strategy": "downloaded-suffix",
    "sourceType": "downloaded",
    "sourceUrl": "../downloaded-portfolio-images/operat-Lagow-zdj15.jpg",
    "confidence": 95,
    "posts": [
      "operat-dendrologiczny-lagowie.md"
    ]
  },
  "/assets/images/portfolio/operat-dendrologiczny-lagowie/operat-lagow-zdj16.jpg": {
    "filename": "operat-lagow-zdj16.jpg",
    "project": "operat-dendrologiczny-lagowie",
    "strategy": "downloaded-suffix",
    "sourceType": "downloaded",
    "sourceUrl": "../downloaded-portfolio-images/operat-Lagow-zdj16.jpg",
    "confidence": 95,
    "posts": [
      "operat-dendrologiczny-lagowie.md"
    ]
  },
  "/assets/images/portfolio/operat-projekt-nasadzen-kompensacyjnych/main.jpg": {
    "filename": "main.jpg",
    "project": "operat-projekt-nasadzen-kompensacyjnych",
    "strategy": "unmatched",
    "sourceType": null,
    "sourceUrl": null,
    "confidence": 0,
    "posts": [
      "operat-projekt-nasadzen-kompensacyjnych.md"
    ]
  },
  "/assets/images/portfolio/operat-projekt-nasadzen-kompensacyjnych/photo1.jpg": {
    "filename": "photo1.jpg",
    "project": "operat-projekt-nasadzen-kompensacyjnych",
    "strategy": "unmatched",
    "sourceType": null,
    "sourceUrl": null,
    "confidence": 0,
    "posts": [
      "operat-projekt-nasadzen-kompensacyjnych.md"
    ]
  },
  "/assets/images/portfolio/operat-projekt-nasadzen-kompensacyjnych/photo2.jpg": {
    "filename": "photo2.jpg",
    "project": "operat-projekt-nasadzen-kompensacyjnych",
    "strategy": "unmatched",
    "sourceType": null,
    "sourceUrl": null,
    "confidence": 0,
    "posts": [
      "operat-projekt-nasadzen-kompensacyjnych.md"
    ]
  },
  "/assets/images/portfolio/operat-projekt-nasadzen-kompensacyjnych/photo3.jpg": {
    "filename": "photo3.jpg",
    "project": "operat-projekt-nasadzen-kompensacyjnych",
    "strategy": "unmatched",
    "sourceType": null,
    "sourceUrl": null,
    "confidence": 0,
    "posts": [
      "operat-projekt-nasadzen-kompensacyjnych.md"
    ]
  },
  "/assets/images/portfolio/operat-projekt-nasadzen-kompensacyjnych/photo4.jpg": {
    "filename": "photo4.jpg",
    "project": "operat-projekt-nasadzen-kompensacyjnych",
    "strategy": "unmatched",
    "sourceType": null,
    "sourceUrl": null,
    "confidence": 0,
    "posts": [
      "operat-projekt-nasadzen-kompensacyjnych.md"
    ]
  },
  "/assets/images/portfolio/opinia-dendrologiczna-dla-debu-pomnika-przyrody/main.jpg": {
    "filename": "main.jpg",
    "project": "opinia-dendrologiczna-dla-debu-pomnika-przyrody",
    "strategy": "unmatched",
    "sourceType": null,
    "sourceUrl": null,
    "confidence": 0,
    "posts": [
      "opinia-dendrologiczna-dla-debu-pomnika-przyrody.md"
    ]
  },
  "/assets/images/portfolio/park-kieszonkowy-ogrod-pereca/Ogrody-Pereca-zdj-1.jpg": {
    "filename": "Ogrody-Pereca-zdj-1.jpg",
    "project": "park-kieszonkowy-ogrod-pereca",
    "strategy": "unmatched",
    "sourceType": null,
    "sourceUrl": null,
    "confidence": 0,
    "posts": [
      "park-kieszonkowy-ogrod-pereca.md"
    ]
  },
  "/assets/images/portfolio/park-kieszonkowy-ogrod-pereca/Ogrody-Pereca-zdj-2.jpg": {
    "filename": "Ogrody-Pereca-zdj-2.jpg",
    "project": "park-kieszonkowy-ogrod-pereca",
    "strategy": "unmatched",
    "sourceType": null,
    "sourceUrl": null,
    "confidence": 0,
    "posts": [
      "park-kieszonkowy-ogrod-pereca.md"
    ]
  },
  "/assets/images/portfolio/park-kieszonkowy-ogrod-pereca/Ogrody-Pereca-zdj-3.jpg": {
    "filename": "Ogrody-Pereca-zdj-3.jpg",
    "project": "park-kieszonkowy-ogrod-pereca",
    "strategy": "unmatched",
    "sourceType": null,
    "sourceUrl": null,
    "confidence": 0,
    "posts": [
      "park-kieszonkowy-ogrod-pereca.md"
    ]
  },
  "/assets/images/portfolio/park-kieszonkowy-ogrod-pereca/ikropka-ogrod-pereca3-min.jpg": {
    "filename": "ikropka-ogrod-pereca3-min.jpg",
    "project": "park-kieszonkowy-ogrod-pereca",
    "strategy": "unmatched",
    "sourceType": null,
    "sourceUrl": null,
    "confidence": 0,
    "posts": [
      "park-kieszonkowy-ogrod-pereca.md"
    ]
  },
  "/assets/images/portfolio/park-kieszonkowy-ogrod-pereca/ikropka-ogrod-pereca1-min.jpg": {
    "filename": "ikropka-ogrod-pereca1-min.jpg",
    "project": "park-kieszonkowy-ogrod-pereca",
    "strategy": "unmatched",
    "sourceType": null,
    "sourceUrl": null,
    "confidence": 0,
    "posts": [
      "park-kieszonkowy-ogrod-pereca.md"
    ]
  },
  "/assets/images/portfolio/park-kieszonkowy-ogrod-pereca/ikropka-ogrod-pereca2-min.jpg": {
    "filename": "ikropka-ogrod-pereca2-min.jpg",
    "project": "park-kieszonkowy-ogrod-pereca",
    "strategy": "unmatched",
    "sourceType": null,
    "sourceUrl": null,
    "confidence": 0,
    "posts": [
      "park-kieszonkowy-ogrod-pereca.md"
    ]
  },
  "/assets/images/portfolio/park-kieszonkowy-ogrod-pereca/ikropka-ogrod-pereca6-min.jpg": {
    "filename": "ikropka-ogrod-pereca6-min.jpg",
    "project": "park-kieszonkowy-ogrod-pereca",
    "strategy": "unmatched",
    "sourceType": null,
    "sourceUrl": null,
    "confidence": 0,
    "posts": [
      "park-kieszonkowy-ogrod-pereca.md"
    ]
  },
  "/assets/images/portfolio/park-kieszonkowy-ogrod-pereca/ikropka-ogrod-pereca7-min.jpg": {
    "filename": "ikropka-ogrod-pereca7-min.jpg",
    "project": "park-kieszonkowy-ogrod-pereca",
    "strategy": "unmatched",
    "sourceType": null,
    "sourceUrl": null,
    "confidence": 0,
    "posts": [
      "park-kieszonkowy-ogrod-pereca.md"
    ]
  },
  "/assets/images/portfolio/park-kieszonkowy-ogrod-pereca/ikropka-ogrod-pereca9-min.jpg": {
    "filename": "ikropka-ogrod-pereca9-min.jpg",
    "project": "park-kieszonkowy-ogrod-pereca",
    "strategy": "unmatched",
    "sourceType": null,
    "sourceUrl": null,
    "confidence": 0,
    "posts": [
      "park-kieszonkowy-ogrod-pereca.md"
    ]
  },
  "/assets/images/portfolio/park-kieszonkowy-ogrod-pereca/ikropka-ogrod-pereca10-min.jpg": {
    "filename": "ikropka-ogrod-pereca10-min.jpg",
    "project": "park-kieszonkowy-ogrod-pereca",
    "strategy": "unmatched",
    "sourceType": null,
    "sourceUrl": null,
    "confidence": 0,
    "posts": [
      "park-kieszonkowy-ogrod-pereca.md"
    ]
  },
  "/assets/images/portfolio/park-kieszonkowy-ogrod-pereca/ikropka-ogrod-pereca12-min.jpg": {
    "filename": "ikropka-ogrod-pereca12-min.jpg",
    "project": "park-kieszonkowy-ogrod-pereca",
    "strategy": "unmatched",
    "sourceType": null,
    "sourceUrl": null,
    "confidence": 0,
    "posts": [
      "park-kieszonkowy-ogrod-pereca.md"
    ]
  },
  "/assets/images/portfolio/park-kieszonkowy-ogrod-pereca/ikropka-ogrod-pereca11-min.jpg": {
    "filename": "ikropka-ogrod-pereca11-min.jpg",
    "project": "park-kieszonkowy-ogrod-pereca",
    "strategy": "unmatched",
    "sourceType": null,
    "sourceUrl": null,
    "confidence": 0,
    "posts": [
      "park-kieszonkowy-ogrod-pereca.md"
    ]
  },
  "/assets/images/portfolio/park-kieszonkowy-ogrod-pereca/ikropka-ogrod-pereca8-min_optimized.jpg": {
    "filename": "ikropka-ogrod-pereca8-min_optimized.jpg",
    "project": "park-kieszonkowy-ogrod-pereca",
    "strategy": "unmatched",
    "sourceType": null,
    "sourceUrl": null,
    "confidence": 0,
    "posts": [
      "park-kieszonkowy-ogrod-pereca.md"
    ]
  },
  "/assets/images/portfolio/park-kieszonkowy-ogrod-pereca/ikropka-ogrod-pereca5-min.jpg": {
    "filename": "ikropka-ogrod-pereca5-min.jpg",
    "project": "park-kieszonkowy-ogrod-pereca",
    "strategy": "unmatched",
    "sourceType": null,
    "sourceUrl": null,
    "confidence": 0,
    "posts": [
      "park-kieszonkowy-ogrod-pereca.md"
    ]
  },
  "/assets/images/portfolio/park-kieszonkowy-ogrod-pereca/ikropka-ogrod-pereca4-min.jpg": {
    "filename": "ikropka-ogrod-pereca4-min.jpg",
    "project": "park-kieszonkowy-ogrod-pereca",
    "strategy": "unmatched",
    "sourceType": null,
    "sourceUrl": null,
    "confidence": 0,
    "posts": [
      "park-kieszonkowy-ogrod-pereca.md"
    ]
  },
  "/assets/images/portfolio/park-kieszonkowy-ogrod-pereca/park-kieszonkowy-pereca-realizacja-min_optimized.jpg": {
    "filename": "park-kieszonkowy-pereca-realizacja-min_optimized.jpg",
    "project": "park-kieszonkowy-ogrod-pereca",
    "strategy": "unmatched",
    "sourceType": null,
    "sourceUrl": null,
    "confidence": 0,
    "posts": [
      "park-kieszonkowy-ogrod-pereca.md"
    ]
  },
  "/assets/images/portfolio/park-kieszonkowy-ogrod-pereca/park-kieszonkowy-pereca-realizacja2-min.jpg": {
    "filename": "park-kieszonkowy-pereca-realizacja2-min.jpg",
    "project": "park-kieszonkowy-ogrod-pereca",
    "strategy": "unmatched",
    "sourceType": null,
    "sourceUrl": null,
    "confidence": 0,
    "posts": [
      "park-kieszonkowy-ogrod-pereca.md"
    ]
  },
  "/assets/images/portfolio/park-kieszonkowy-ogrod-pereca/park-kieszonkowy-pereca-realizacja3-min_optimized.jpg": {
    "filename": "park-kieszonkowy-pereca-realizacja3-min_optimized.jpg",
    "project": "park-kieszonkowy-ogrod-pereca",
    "strategy": "unmatched",
    "sourceType": null,
    "sourceUrl": null,
    "confidence": 0,
    "posts": [
      "park-kieszonkowy-ogrod-pereca.md"
    ]
  },
  "/assets/images/portfolio/park-kieszonkowy-ogrod-pereca/Ogrody-Pereca-zdj-8.jpg": {
    "filename": "Ogrody-Pereca-zdj-8.jpg",
    "project": "park-kieszonkowy-ogrod-pereca",
    "strategy": "unmatched",
    "sourceType": null,
    "sourceUrl": null,
    "confidence": 0,
    "posts": [
      "park-kieszonkowy-ogrod-pereca.md"
    ]
  },
  "/assets/images/portfolio/park-kieszonkowy-ogrod-pereca/Ogrody-Pereca-zdj-5.jpg": {
    "filename": "Ogrody-Pereca-zdj-5.jpg",
    "project": "park-kieszonkowy-ogrod-pereca",
    "strategy": "unmatched",
    "sourceType": null,
    "sourceUrl": null,
    "confidence": 0,
    "posts": [
      "park-kieszonkowy-ogrod-pereca.md"
    ]
  },
  "/assets/images/portfolio/park-kieszonkowy-ogrod-pereca/Ogrody-Pereca-zdj-9-min.jpg": {
    "filename": "Ogrody-Pereca-zdj-9-min.jpg",
    "project": "park-kieszonkowy-ogrod-pereca",
    "strategy": "unmatched",
    "sourceType": null,
    "sourceUrl": null,
    "confidence": 0,
    "posts": [
      "park-kieszonkowy-ogrod-pereca.md"
    ]
  },
  "/assets/images/portfolio/park-kieszonkowy-ogrod-pereca/Ogrody-Pereca-zdj-10.jpg": {
    "filename": "Ogrody-Pereca-zdj-10.jpg",
    "project": "park-kieszonkowy-ogrod-pereca",
    "strategy": "unmatched",
    "sourceType": null,
    "sourceUrl": null,
    "confidence": 0,
    "posts": [
      "park-kieszonkowy-ogrod-pereca.md"
    ]
  },
  "/assets/images/portfolio/park-kieszonkowy-pod-srebrzystym-klonem/main.jpg": {
    "filename": "main.jpg",
    "project": "park-kieszonkowy-pod-srebrzystym-klonem",
    "strategy": "unmatched",
    "sourceType": null,
    "sourceUrl": null,
    "confidence": 0,
    "posts": [
      "park-kieszonkowy-pod-srebrzystym-klonem.md"
    ]
  },
  "/assets/images/portfolio/park-kieszonkowy-pod-srebrzystym-klonem/photo2.jpg": {
    "filename": "photo2.jpg",
    "project": "park-kieszonkowy-pod-srebrzystym-klonem",
    "strategy": "unmatched",
    "sourceType": null,
    "sourceUrl": null,
    "confidence": 0,
    "posts": [
      "park-kieszonkowy-pod-srebrzystym-klonem.md"
    ]
  },
  "/assets/images/portfolio/park-kieszonkowy-pod-srebrzystym-klonem/photo3.jpg": {
    "filename": "photo3.jpg",
    "project": "park-kieszonkowy-pod-srebrzystym-klonem",
    "strategy": "unmatched",
    "sourceType": null,
    "sourceUrl": null,
    "confidence": 0,
    "posts": [
      "park-kieszonkowy-pod-srebrzystym-klonem.md"
    ]
  },
  "/assets/images/portfolio/park-kieszonkowy-pod-srebrzystym-klonem/photo4.jpg": {
    "filename": "photo4.jpg",
    "project": "park-kieszonkowy-pod-srebrzystym-klonem",
    "strategy": "unmatched",
    "sourceType": null,
    "sourceUrl": null,
    "confidence": 0,
    "posts": [
      "park-kieszonkowy-pod-srebrzystym-klonem.md"
    ]
  },
  "/assets/images/portfolio/park-kieszonkowy-pod-srebrzystym-klonem/photo5.jpg": {
    "filename": "photo5.jpg",
    "project": "park-kieszonkowy-pod-srebrzystym-klonem",
    "strategy": "unmatched",
    "sourceType": null,
    "sourceUrl": null,
    "confidence": 0,
    "posts": [
      "park-kieszonkowy-pod-srebrzystym-klonem.md"
    ]
  },
  "/assets/images/portfolio/park-kieszonkowy-pod-srebrzystym-klonem/photo6.jpg": {
    "filename": "photo6.jpg",
    "project": "park-kieszonkowy-pod-srebrzystym-klonem",
    "strategy": "unmatched",
    "sourceType": null,
    "sourceUrl": null,
    "confidence": 0,
    "posts": [
      "park-kieszonkowy-pod-srebrzystym-klonem.md"
    ]
  },
  "/assets/images/portfolio/park-kieszonkowy-pod-srebrzystym-klonem/photo7.jpg": {
    "filename": "photo7.jpg",
    "project": "park-kieszonkowy-pod-srebrzystym-klonem",
    "strategy": "unmatched",
    "sourceType": null,
    "sourceUrl": null,
    "confidence": 0,
    "posts": [
      "park-kieszonkowy-pod-srebrzystym-klonem.md"
    ]
  },
  "/assets/images/portfolio/park-kieszonkowy-pod-srebrzystym-klonem/photo8.jpg": {
    "filename": "photo8.jpg",
    "project": "park-kieszonkowy-pod-srebrzystym-klonem",
    "strategy": "unmatched",
    "sourceType": null,
    "sourceUrl": null,
    "confidence": 0,
    "posts": [
      "park-kieszonkowy-pod-srebrzystym-klonem.md"
    ]
  },
  "/assets/images/portfolio/park-kieszonkowy-pod-srebrzystym-klonem/photo9.jpg": {
    "filename": "photo9.jpg",
    "project": "park-kieszonkowy-pod-srebrzystym-klonem",
    "strategy": "unmatched",
    "sourceType": null,
    "sourceUrl": null,
    "confidence": 0,
    "posts": [
      "park-kieszonkowy-pod-srebrzystym-klonem.md"
    ]
  },
  "/assets/images/portfolio/park-mlodziezowy-w-swidnicy/Park-Mlodziezowy-slider-1.jpg": {
    "filename": "Park-Mlodziezowy-slider-1.jpg",
    "project": "park-mlodziezowy-w-swidnicy",
    "strategy": "unmatched",
    "sourceType": null,
    "sourceUrl": null,
    "confidence": 0,
    "posts": [
      "park-mlodziezowy-w-swidnicy.md"
    ]
  },
  "/assets/images/portfolio/park-mlodziezowy-w-swidnicy/Park-Mlodziezowy-zdj.jpg": {
    "filename": "Park-Mlodziezowy-zdj.jpg",
    "project": "park-mlodziezowy-w-swidnicy",
    "strategy": "unmatched",
    "sourceType": null,
    "sourceUrl": null,
    "confidence": 0,
    "posts": [
      "park-mlodziezowy-w-swidnicy.md"
    ]
  },
  "/assets/images/portfolio/park-mlodziezowy-w-swidnicy/Park-Mlodziezowy-zdj4-1.jpg": {
    "filename": "Park-Mlodziezowy-zdj4-1.jpg",
    "project": "park-mlodziezowy-w-swidnicy",
    "strategy": "unmatched",
    "sourceType": null,
    "sourceUrl": null,
    "confidence": 0,
    "posts": [
      "park-mlodziezowy-w-swidnicy.md"
    ]
  },
  "/assets/images/portfolio/park-mlodziezowy-w-swidnicy/Park-Mlodziezowy-zdj5-1.jpg": {
    "filename": "Park-Mlodziezowy-zdj5-1.jpg",
    "project": "park-mlodziezowy-w-swidnicy",
    "strategy": "unmatched",
    "sourceType": null,
    "sourceUrl": null,
    "confidence": 0,
    "posts": [
      "park-mlodziezowy-w-swidnicy.md"
    ]
  },
  "/assets/images/portfolio/park-mlodziezowy-w-swidnicy/Park-Mlodziezowy-zdj2-1.jpg": {
    "filename": "Park-Mlodziezowy-zdj2-1.jpg",
    "project": "park-mlodziezowy-w-swidnicy",
    "strategy": "unmatched",
    "sourceType": null,
    "sourceUrl": null,
    "confidence": 0,
    "posts": [
      "park-mlodziezowy-w-swidnicy.md"
    ]
  },
  "/assets/images/portfolio/park-mlodziezowy-w-swidnicy/Park-Mlodziezowy-zdj3-1.jpg": {
    "filename": "Park-Mlodziezowy-zdj3-1.jpg",
    "project": "park-mlodziezowy-w-swidnicy",
    "strategy": "unmatched",
    "sourceType": null,
    "sourceUrl": null,
    "confidence": 0,
    "posts": [
      "park-mlodziezowy-w-swidnicy.md"
    ]
  },
  "/assets/images/portfolio/park-mlodziezowy-w-swidnicy/Park-Mlodziezowy-zdj1-1.jpg": {
    "filename": "Park-Mlodziezowy-zdj1-1.jpg",
    "project": "park-mlodziezowy-w-swidnicy",
    "strategy": "unmatched",
    "sourceType": null,
    "sourceUrl": null,
    "confidence": 0,
    "posts": [
      "park-mlodziezowy-w-swidnicy.md"
    ]
  },
  "/assets/images/portfolio/park-przygody-w-parku-andersa/layout_slider_Andersa_do-500KB.jpg": {
    "filename": "layout_slider_Andersa_do-500KB.jpg",
    "project": "park-przygody-w-parku-andersa",
    "strategy": "unmatched",
    "sourceType": null,
    "sourceUrl": null,
    "confidence": 0,
    "posts": [
      "park-przygody-w-parku-andersa.md"
    ]
  },
  "/assets/images/portfolio/park-przygody-w-parku-andersa/Park-Andersa-hustawki-podsatawowy_Ikropka.png": {
    "filename": "Park-Andersa-hustawki-podsatawowy_Ikropka.png",
    "project": "park-przygody-w-parku-andersa",
    "strategy": "unmatched",
    "sourceType": null,
    "sourceUrl": null,
    "confidence": 0,
    "posts": [
      "park-przygody-w-parku-andersa.md"
    ]
  },
  "/assets/images/portfolio/park-przygody-w-parku-andersa/Park-Andersa-przygoda-podstawowy_Ikropka.png": {
    "filename": "Park-Andersa-przygoda-podstawowy_Ikropka.png",
    "project": "park-przygody-w-parku-andersa",
    "strategy": "unmatched",
    "sourceType": null,
    "sourceUrl": null,
    "confidence": 0,
    "posts": [
      "park-przygody-w-parku-andersa.md"
    ]
  },
  "/assets/images/portfolio/park-przygody-w-parku-andersa/Park-Andersa-sport-podstawowy_Ikropka.png": {
    "filename": "Park-Andersa-sport-podstawowy_Ikropka.png",
    "project": "park-przygody-w-parku-andersa",
    "strategy": "unmatched",
    "sourceType": null,
    "sourceUrl": null,
    "confidence": 0,
    "posts": [
      "park-przygody-w-parku-andersa.md"
    ]
  },
  "/assets/images/portfolio/park-przygody-w-parku-andersa/Park-Andersa-zdrowie-podstawowy_Ikropka.png": {
    "filename": "Park-Andersa-zdrowie-podstawowy_Ikropka.png",
    "project": "park-przygody-w-parku-andersa",
    "strategy": "unmatched",
    "sourceType": null,
    "sourceUrl": null,
    "confidence": 0,
    "posts": [
      "park-przygody-w-parku-andersa.md"
    ]
  },
  "/assets/images/portfolio/park-przygody-w-parku-andersa/layout_grafika-do-galerii_wyzszy_rzut.jpg": {
    "filename": "layout_grafika-do-galerii_wyzszy_rzut.jpg",
    "project": "park-przygody-w-parku-andersa",
    "strategy": "unmatched",
    "sourceType": null,
    "sourceUrl": null,
    "confidence": 0,
    "posts": [
      "park-przygody-w-parku-andersa.md"
    ]
  },
  "/assets/images/portfolio/park-przygody-w-parku-andersa/zestawienie-roślinności-layout-Andersa.jpg": {
    "filename": "zestawienie-roślinności-layout-Andersa.jpg",
    "project": "park-przygody-w-parku-andersa",
    "strategy": "unmatched",
    "sourceType": null,
    "sourceUrl": null,
    "confidence": 0,
    "posts": [
      "park-przygody-w-parku-andersa.md"
    ]
  },
  "/assets/images/portfolio/park-przygody-w-parku-andersa/zestawienie-roślinności-layout-Andersa_2.jpg": {
    "filename": "zestawienie-roślinności-layout-Andersa_2.jpg",
    "project": "park-przygody-w-parku-andersa",
    "strategy": "unmatched",
    "sourceType": null,
    "sourceUrl": null,
    "confidence": 0,
    "posts": [
      "park-przygody-w-parku-andersa.md"
    ]
  },
  "/assets/images/portfolio/park-w-bialaczowie/main.jpg": {
    "filename": "main.jpg",
    "project": "park-w-bialaczowie",
    "strategy": "unmatched",
    "sourceType": null,
    "sourceUrl": null,
    "confidence": 0,
    "posts": [
      "park-w-bialaczowie.md"
    ]
  },
  "/assets/images/portfolio/pomniki-przyrody-strzelinie/slider11.jpg": {
    "filename": "slider11.jpg",
    "project": "pomniki-przyrody-strzelinie",
    "strategy": "downloaded-suffix",
    "sourceType": "downloaded",
    "sourceUrl": "../downloaded-portfolio-images/Ekspertyza-4-drzew-slider11.jpg",
    "confidence": 95,
    "posts": [
      "pomniki-przyrody-strzelinie.md"
    ]
  },
  "/assets/images/portfolio/pomniki-przyrody-strzelinie/zdj-1.jpg": {
    "filename": "zdj-1.jpg",
    "project": "pomniki-przyrody-strzelinie",
    "strategy": "downloaded-suffix",
    "sourceType": "downloaded",
    "sourceUrl": "../downloaded-portfolio-images/Alejowe-Arboretum-zdj-1.jpg",
    "confidence": 95,
    "posts": [
      "pomniki-przyrody-strzelinie.md"
    ]
  },
  "/assets/images/portfolio/pomniki-przyrody-strzelinie/zdj-2.jpg": {
    "filename": "zdj-2.jpg",
    "project": "pomniki-przyrody-strzelinie",
    "strategy": "downloaded-suffix",
    "sourceType": "downloaded",
    "sourceUrl": "../downloaded-portfolio-images/Alejowe-Arboretum-zdj-2.jpg",
    "confidence": 95,
    "posts": [
      "pomniki-przyrody-strzelinie.md"
    ]
  },
  "/assets/images/portfolio/pomniki-przyrody-strzelinie/zdj-3.jpg": {
    "filename": "zdj-3.jpg",
    "project": "pomniki-przyrody-strzelinie",
    "strategy": "downloaded-suffix",
    "sourceType": "downloaded",
    "sourceUrl": "../downloaded-portfolio-images/Alejowe-Arboretum-zdj-3.jpg",
    "confidence": 95,
    "posts": [
      "pomniki-przyrody-strzelinie.md"
    ]
  },
  "/assets/images/portfolio/pomniki-przyrody-strzelinie/zdj-4.jpg": {
    "filename": "zdj-4.jpg",
    "project": "pomniki-przyrody-strzelinie",
    "strategy": "downloaded-suffix",
    "sourceType": "downloaded",
    "sourceUrl": "../downloaded-portfolio-images/Alejowe-Arboretum-zdj-4.jpg",
    "confidence": 95,
    "posts": [
      "pomniki-przyrody-strzelinie.md"
    ]
  },
  "/assets/images/portfolio/pomniki-przyrody-strzelinie/zdj-5.jpg": {
    "filename": "zdj-5.jpg",
    "project": "pomniki-przyrody-strzelinie",
    "strategy": "downloaded-suffix",
    "sourceType": "downloaded",
    "sourceUrl": "../downloaded-portfolio-images/Alejowe-Arboretum-zdj-5.jpg",
    "confidence": 95,
    "posts": [
      "pomniki-przyrody-strzelinie.md"
    ]
  },
  "/assets/images/portfolio/pomniki-przyrody-strzelinie/zdj-6.jpg": {
    "filename": "zdj-6.jpg",
    "project": "pomniki-przyrody-strzelinie",
    "strategy": "downloaded-suffix",
    "sourceType": "downloaded",
    "sourceUrl": "../downloaded-portfolio-images/Alejowe-Arboretum-zdj-6.jpg",
    "confidence": 95,
    "posts": [
      "pomniki-przyrody-strzelinie.md"
    ]
  }
}